{
  "parent": "minecraft:recipes/root",
  "criteria": {
    "has_block_rubber": {
      "conditions": {
        "items": [
          {
            "items": [
              "hbm:block_rubber"
            ]
          }
        ]
      },
      "trigger": "minecraft:inventory_changed"
    },
    "has_the_recipe": {
      "conditions": {
        "recipe": "minecraft:block_rubber_to_ingot_rubber"
      },
      "trigger": "minecraft:recipe_unlocked"
    }
  },
  "requirements": [
    [
      "has_block_rubber",
      "has_the_recipe"
    ]
  ],
  "rewards": {
    "recipes": [
      "minecraft:block_rubber_to_ingot_rubber"
    ]
  },
  "sends_telemetry_event": false
}